.gitignore
README.md
pyproject.toml
requirements.txt
setup.cfg
setup.py
stdeb.cfg
.github/workflows/test.yml
motmot/__init__.py
motmot.ufmf.egg-info/PKG-INFO
motmot.ufmf.egg-info/SOURCES.txt
motmot.ufmf.egg-info/dependency_links.txt
motmot.ufmf.egg-info/entry_points.txt
motmot.ufmf.egg-info/namespace_packages.txt
motmot.ufmf.egg-info/top_level.txt
motmot/ufmf/__init__.py
motmot/ufmf/fmf2ufmf.py
motmot/ufmf/reindex.py
motmot/ufmf/tests.py
motmot/ufmf/ufmf.py
motmot/ufmf/ufmf2fmf.py
motmot/ufmf/ufmf_1to3.py
motmot/ufmf/ufmf_2to3.py
motmot/ufmf/ufmfcat.py
motmot/ufmf/ufmfstats.py