Metadata-Version: 1.0
Name: motmot.ufmf
Version: 0.4.2
Summary: micro-fmf (.ufmf) format library
Home-page: UNKNOWN
Author: Andrew Straw
Author-email: strawman@astraw.com
License: UNKNOWN
Platform: UNKNOWN
